wolkstack.py
wolkstack/__init__.py
wolkstack/cli_tools.py
wolkstack/main.py
wolkstack/wolk.py
wolkstack/cli/__init__.py
wolkstack/cli/main.py
wolkstack/cli/groups/__init__.py
wolkstack/cli/groups/cluster.py
wolkstack/groups/__init__.py
wolkstack/groups/cli_tools.py
wolkstack/tools/__init__.py
wolkstack/tools/docker-compose.py
wolkstack/tools/helm.py
wolkstack/tools/kubectl.py
wolkstack/tools/terraform.py
wolkstack/utils/__init__.py
wolkstack/utils/constants.py
wolkstack/utils/helpers.py
Wolkstack-1.1.1.dist-info/LICENSE
Wolkstack-1.1.1.dist-info/METADATA
Wolkstack-1.1.1.dist-info/WHEEL
Wolkstack-1.1.1.dist-info/dependency_links.txt
Wolkstack-1.1.1.dist-info/entry_points.txt
Wolkstack-1.1.1.dist-info/top_level.txt
Wolkstack-1.1.1.dist-info/RECORD
