Metadata-Version: 2.1
Name: Wolkstack
Version: 1.1.1
Summary: A Framework for blazing fast cloud infrastructure management and deployment
Home-page: https://github.com/liannus/wolkstack
Author: Josh Gorman
Author-email: josh-gorman@hotmail.com
License: MIT
Platform: UNKNOWN
Classifier: License :: OSI Approved :: MIT License
Classifier: Programming Language :: Python :: 3
Classifier: Programming Language :: Python :: 3.7
Requires-Python: >=3.7
Requires-Dist: click (==7.1.2)
Requires-Dist: cookiecutter (==1.7.2)
Requires-Dist: PyYAML (==5.3.1)
